README.rst
setup.py
django_souvenirs.egg-info/PKG-INFO
django_souvenirs.egg-info/SOURCES.txt
django_souvenirs.egg-info/dependency_links.txt
django_souvenirs.egg-info/requires.txt
django_souvenirs.egg-info/top_level.txt
souvenirs/__init__.py
souvenirs/control.py
souvenirs/middleware.py
souvenirs/models.py
souvenirs/reports.py
souvenirs/utils.py
souvenirs/management/__init__.py
souvenirs/management/commands/__init__.py
souvenirs/management/commands/_commands.py
souvenirs/management/commands/_helpers.py
souvenirs/management/commands/show_usage.py
souvenirs/migrations/0001_initial.py
souvenirs/migrations/__init__.py
souvenirs/tests/__init__.py
souvenirs/tests/factories.py
souvenirs/tests/test_commands.py
souvenirs/tests/test_middleware.py
souvenirs/tests/test_models.py
souvenirs/tests/test_reports.py
souvenirs/tests/test_utils.py