Metadata-Version: 1.1
Name: django-souvenirs
Version: 0.1
Summary: Django app for efficiently measuring usage
Home-page: https://github.com/appsembler/django-souvenirs
Author: Aron Griffis
Author-email: aron@scampersand.com
License: MIT
Keywords: django,reusable,souvenirs,metrics,usage,tracking
Platform: OS Independent
Classifier: Development Status :: 5 - Production/Stable
Classifier: Intended Audience :: Developers
Classifier: License :: OSI Approved :: MIT License
Classifier: Programming Language :: Python
Classifier: Programming Language :: Python :: 2
Classifier: Programming Language :: Python :: 2.7
Classifier: Programming Language :: Python :: 3
Classifier: Programming Language :: Python :: 3.5
Classifier: Programming Language :: Python :: 3.6
